README.md
pyproject.toml
pyshapley/__init__.py
pyshapley/game.py
pyshapley/solution.py
pyshapley/util.py
pyshapley-0.1.0.dist-info/LICENSE
pyshapley-0.1.0.dist-info/WHEEL
pyshapley-0.1.0.dist-info/METADATA
pyshapley-0.1.0.dist-info/RECORD
