Metadata-Version: 2.1
Name: pyshapley
Version: 0.1.0
Summary: Library for computing Shapley values of coalitional games
Home-page: https://github.com/JulianStier/pyshapley
License: MIT
Keywords: shapley value,coalitional games,game theory,shap
Author: Julian Stier
Author-email: julian.stier@uni-passau.de
Requires-Python: >=3.8,<4.0
Classifier: License :: OSI Approved :: MIT License
Classifier: Programming Language :: Python :: 3
Classifier: Programming Language :: Python :: 3.10
Classifier: Programming Language :: Python :: 3.8
Classifier: Programming Language :: Python :: 3.9
Requires-Dist: deprecated (>=1.2.10,<2.0.0)
Requires-Dist: importlib-metadata (>=4.4,<5.0)
Requires-Dist: importlib-resources (>=5.0,<6.0)
Requires-Dist: numpy (>=1.22,<2.0)
Requires-Dist: semantic_version (>=2.10,<3.0)
Project-URL: Repository, https://github.com/JulianStier/pyshapley
